{"3adae761e22b37c7cefc5c49f8a875f7edabc92df31dfc3a0329179a3f2dcb14": {"text_length": 266, "result": {"score": 23.96169191492615, "originality_level": "High", "similarity_range": "0-30%", "confidence": "High", "analysis_summary": "Passed local heuristic checks. Content seems highly original.", "matched_patterns": ["local analysis"], "api_used": false, "sources": []}, "timestamp": "2026-02-25T21:51:51.073503"}, "f2da37197513cedd208179c48d12f6c764b453f216e09296f03d973308933fcf": {"text_length": 121, "result": {"score": 18.46372364689991, "originality_level": "High", "similarity_range": "0-30%", "confidence": "High", "analysis_summary": "Passed local heuristic checks. Content seems highly original.", "matched_patterns": ["local analysis"], "api_used": false, "sources": []}, "timestamp": "2026-02-25T22:14:30.502624"}, "63025d5125504fe753287ebe541b8091c352de6c3c37d5aa48403dea00ccc7db": {"text_length": 2780, "result": {"score": 14.649999999999999, "originality_level": "High", "similarity_range": "0-30%", "confidence": "High", "analysis_summary": "Passed local heuristic checks. Content seems highly original.", "matched_patterns": ["local analysis"], "api_used": false, "sources": []}, "timestamp": "2026-02-25T22:16:44.020819"}, "0c9b043f9385a732ef09439ed69c1b0fe50888328e36f9f51bc3737e8015a54e": {"text_length": 10486, "result": {"score": 30.273418863053614, "originality_level": "Medium", "similarity_range": "30-45%", "confidence": "Medium", "analysis_summary": "The text follows a common template for SaaS product briefs and includes generic sections (overview, user personas, problem statement, workflow steps) that appear in many similar tool descriptions, indicating moderate overlap but also original specifics about Authentiq.", "matched_patterns": ["Repeated section headings like 'What this software does' and 'Who the users are'", "Standard workflow enumeration with API endpoint patterns", "Common phrasing about free vs paid limits and AI detection features"], "api_used": true, "sources": []}, "timestamp": "2026-02-25T22:33:57.159478"}, "440bc4182203753cf360007a0496c571e971b7f357b063d4816b1748c8177b16": {"text_length": 415, "result": {"score": 23.16, "originality_level": "High", "similarity_range": "0-30%", "confidence": "High", "analysis_summary": "Passed local heuristic checks. Content seems highly original.", "matched_patterns": ["local analysis"], "api_used": false, "sources": []}, "timestamp": "2026-02-25T23:01:37.896660"}, "9ca9467d054deb4d2bec0e0c6ac1d79b0c5218e34c16b5d52ed5a5b931a8fa23": {"text_length": 949, "result": {"score": 31.960138605029652, "originality_level": "Medium", "similarity_range": "40-60%", "confidence": "Medium", "analysis_summary": "The passage is a collection of factual Q&A and matching items that appear in many educational worksheets, indicating moderate similarity to existing sources.", "matched_patterns": ["matching question format", "list of famous personalities with brief descriptions", "standard factual Q&A pairs"], "api_used": true, "sources": []}, "timestamp": "2026-02-25T23:07:59.223598"}, "f6e5b918d298d51526dd4464fb5eb474f9df3e560cc4d58d85c0fd6520930a54": {"text_length": 1804, "result": {"score": 25.1, "originality_level": "High", "similarity_range": "0-30%", "confidence": "High", "analysis_summary": "Passed local heuristic checks. Content seems highly original.", "matched_patterns": ["local analysis"], "api_used": false, "sources": []}, "timestamp": "2026-02-26T23:01:00.535495"}, "3f2bf5fcf65ca10a3cb5317e859117ec52028ba3495886d45d6e9198ef6280e4": {"text_length": 114, "result": {"score": 33.96831102433788, "originality_level": "High", "similarity_range": "0-20%", "confidence": "Medium", "analysis_summary": "The sentence is a generic test statement with no distinctive phrasing that would appear in published sources, indicating minimal overlap.", "matched_patterns": ["generic test phrasing", "boilerplate language"], "api_used": true, "sources": []}, "timestamp": "2026-02-28T22:18:14.472513"}, "4c697c8ccdbd0cb0781d3de5e1fa3adbff14360c36b76cd0c8487371b91c51d7": {"text_length": 74, "result": {"score": 82.915619758885, "originality_level": "Low", "similarity_range": "70-90%", "confidence": "Medium", "analysis_summary": "The sentence largely reproduces the classic pangram 'The quick brown fox jumps over the lazy dog', a well\u2011known source, with only a minor addition.", "matched_patterns": ["The quick brown fox jumps over the lazy dog"], "api_used": true, "sources": []}, "timestamp": "2026-02-28T22:35:41.201309"}, "6c18c1b7e3b194692f6590382242404fd4d535b7381d60f26ed1941f48594257": {"text_length": 81, "result": {"score": 23.14550249431379, "originality_level": "High", "similarity_range": "0-30%", "confidence": "High", "analysis_summary": "Passed local heuristic checks. Content seems highly original.", "matched_patterns": ["local analysis"], "api_used": false, "sources": []}, "timestamp": "2026-02-28T23:02:24.699727"}, "379f0a8e0e7c33051f9159d656ff66e696a7c212977b408b17d00cfe3aaa5bbe": {"text_length": 1734, "result": {"score": 15.89, "originality_level": "High", "similarity_range": "0-30%", "confidence": "High", "analysis_summary": "Passed local heuristic checks. Content seems highly original.", "matched_patterns": ["local analysis"], "api_used": false, "sources": []}, "timestamp": "2026-02-28T23:10:44.092010"}, "2d219917ee61a169805d8ea470406737eac41f4a7652f3aa704c406c366f4453": {"text_length": 4142, "result": {"score": 14.668408643629121, "originality_level": "High", "similarity_range": "0-30%", "confidence": "High", "analysis_summary": "Passed local heuristic checks. Content seems highly original.", "matched_patterns": ["local analysis"], "api_used": false, "sources": []}, "timestamp": "2026-02-28T23:18:07.358240"}, "029fe2cd943a45a64cfa989d9ea70f3714fb559036dd4a9c2e6590d38decc66d": {"text_length": 110, "result": {"score": 26.31806779839076, "originality_level": "High", "similarity_range": "0-30%", "confidence": "High", "analysis_summary": "Passed local heuristic checks. Content seems highly original.", "matched_patterns": ["local analysis"], "api_used": false, "sources": []}, "timestamp": "2026-02-28T23:32:35.814769"}, "9658af11452f1e92ab9c268e64916c09bca0721fd86194af1983c0b6cd19a164": {"text_length": 1137, "result": {"score": 18.76, "originality_level": "High", "similarity_range": "0-30%", "confidence": "High", "analysis_summary": "Passed local heuristic checks. Content seems highly original.", "matched_patterns": ["local analysis"], "api_used": false, "sources": []}, "timestamp": "2026-03-01T19:40:51.874645"}}